redbiom/__init__.py
redbiom/_requests.py
redbiom/admin.py
redbiom/fetch.py
redbiom/metadata.py
redbiom/qiita_loader.py
redbiom/search.py
redbiom/set_expr.py
redbiom/summarize.py
redbiom/util.py
redbiom/where_expr.py
redbiom/commands/__init__.py
redbiom/commands/admin.py
redbiom/commands/fetch.py
redbiom/commands/search.py
redbiom/commands/select.py
redbiom/commands/summarize.py
redbiom/tests/__init__.py
redbiom/tests/test_admin.py
redbiom/tests/test_fetch.py
redbiom/tests/test_metadata.py
redbiom/tests/test_requests.py
redbiom/tests/test_rest.py
redbiom/tests/test_search.py
redbiom/tests/test_set_expr.py
redbiom/tests/test_summarize.py
redbiom/tests/test_util.py
redbiom/tests/test_where_expr.py
redbiom-0.3.1.dist-info/METADATA
redbiom-0.3.1.dist-info/RECORD
redbiom-0.3.1.dist-info/WHEEL
redbiom-0.3.1.dist-info/entry_points.txt
redbiom-0.3.1.dist-info/top_level.txt
