Metadata-Version: 2.1
Name: redbiom
Version: 0.3.1
Summary: UNKNOWN
Home-page: https://github.com/biocore/redbiom
Author: Daniel McDonald
Author-email: wasade@gmail.com
License: BSD-3-Clause
Platform: UNKNOWN
Requires-Dist: click (>=6.7)
Requires-Dist: biom-format (>=2.1.5)
Requires-Dist: requests
Requires-Dist: h5py
Requires-Dist: pandas
Requires-Dist: nltk
Requires-Dist: joblib
Requires-Dist: scikit-bio (>=0.4.2)
Requires-Dist: msgpack
